{"464244812":{"login":"464244812","createTime":1620786176633},"azl397985856":{"login":"azl397985856","createTime":1620786176633},"hillsonziqiu":{"login":"hillsonziqiu","createTime":1620786176633},"Forschers":{"login":"Forschers","createTime":1620786176633},"ssxgit":{"login":"ssxgit","createTime":1620786176633},"sumukeio":{"login":"sumukeio","createTime":1620786176633},"ziwh":{"login":"ziwh","createTime":1620786176633},"JasonQiu":{"login":"JasonQiu","createTime":1620786176633},"yeanli95":{"login":"yeanli95","createTime":1620786176633},"yunli2015":{"login":"yunli2015","createTime":1620786176633},"linearindep":{"login":"linearindep","createTime":1620786176633},"liandmin":{"login":"liandmin","createTime":1620786176633},"sunshineliu6":{"login":"sunshineliu6","createTime":1620786176633},"Huzhixin00":{"login":"Huzhixin00","createTime":1620786176633},"LeahLuo0903":{"login":"LeahLuo0903","createTime":1620786176633},"HackBL":{"login":"HackBL","createTime":1620786176634},"mozro0327":{"login":"mozro0327","createTime":1620786176634},"liucy0417":{"login":"liucy0417","createTime":1620786176634},"watermelonDrip":{"login":"watermelonDrip","createTime":1620786176634},"wonderful1234":{"login":"wonderful1234","createTime":1620786176634},"SWUFEzyf":{"login":"SWUFEzyf","createTime":1620786176634},"suffocatingly0":{"login":"suffocatingly0","createTime":1620786176634},"christ36":{"login":"christ36","createTime":1620786176634},"evil-lin":{"login":"evil-lin","createTime":1620786176634},"NchuYJ":{"login":"NchuYJ","createTime":1620786176634},"zc-githubs":{"login":"zc-githubs","createTime":1620786176634},"paopaohua":{"login":"paopaohua","createTime":1620786176634},"Critsu":{"login":"Critsu","createTime":1620786176634},"Placeholder":{"login":"Placeholder","createTime":1620786176634},"Levix":{"login":"Levix","createTime":1620786176634},"newVincentFong":{"login":"newVincentFong","createTime":1620786176634},"cyaoyao":{"login":"cyaoyao","createTime":1620786176634},"cengjingeng":{"login":"cengjingeng","createTime":1620786176634},"hengyi666":{"login":"hengyi666","createTime":1620786176634},"fzzfgbw":{"login":"fzzfgbw","createTime":1620786176634},"Erika2001":{"login":"Erika2001","createTime":1620786176634},"1998yyh":{"login":"1998yyh","createTime":1620786176634},"LexieLiu01":{"login":"LexieLiu01","createTime":1620786176634},"javanlu123":{"login":"javanlu123","createTime":1620786176634},"chelseachen007":{"login":"chelseachen007","createTime":1620786176634},"yuris304":{"login":"yuris304","createTime":1620786176634},"fangyh":{"login":"fangyh","createTime":1620786176634},"fyyjyx-github":{"login":"fyyjyx-github","createTime":1620786176634},"littlesugarman":{"login":"littlesugarman","createTime":1620786176634},"LASIWan":{"login":"LASIWan","createTime":1620786176634},"gitigor107":{"login":"gitigor107","createTime":1620786176634},"DADAHUI":{"login":"DADAHUI","createTime":1620786176634},"yangjiahao106":{"login":"yangjiahao106","createTime":1620786176634},"He1xin":{"login":"He1xin","createTime":1620786176634},"okbug":{"login":"okbug","createTime":1620786176634},"zliu1413":{"login":"zliu1413","createTime":1620786176634},"BeBraveBeCurious":{"login":"BeBraveBeCurious","createTime":1620786176634},"lzcyx":{"login":"lzcyx","createTime":1620786176634},"suikataro":{"login":"suikataro","createTime":1620786176634},"DIUDIU110":{"login":"DIUDIU110","createTime":1620786176634},"DAXIAdaxia":{"login":"DAXIAdaxia","createTime":1620786176634},"tongxw":{"login":"tongxw","createTime":1620786176634},"lingquan02":{"login":"lingquan02","createTime":1620786176634},"taojin1992":{"login":"taojin1992","createTime":1620786176634},"size-of":{"login":"size-of","createTime":1620786176634},"ARe99s":{"login":"ARe99s","createTime":1620786176634},"agentzzz":{"login":"agentzzz","createTime":1620786176634},"longlonglu":{"login":"longlonglu","createTime":1620786176634},"lanceli424":{"login":"lanceli424","createTime":1620786176634},"Saberfish":{"login":"Saberfish","createTime":1620786176634},"zyycode":{"login":"zyycode","createTime":1620786176634},"911gt5":{"login":"911gt5","createTime":1620786176634},"MangoJuicy":{"login":"MangoJuicy","createTime":1620786176634},"yourspeace":{"login":"yourspeace","createTime":1620786176634},"physicshi":{"login":"physicshi","createTime":1620786176634},"SeventeenCui":{"login":"SeventeenCui","createTime":1620786176634},"KevinWorkSpace":{"login":"KevinWorkSpace","createTime":1620786176634},"Cartie-ZhouMo":{"login":"Cartie-ZhouMo","createTime":1620786176634},"fenglei110":{"login":"fenglei110","createTime":1620786176634},"Kuroky-Chen":{"login":"Kuroky-Chen","createTime":1620786176634},"liuhl06":{"login":"liuhl06","createTime":1620786176634},"absent1353":{"login":"absent1353","createTime":1620786176634},"doubelejjyy":{"login":"doubelejjyy","createTime":1620786176634},"andyyxw":{"login":"andyyxw","createTime":1620786176634},"pkuphy":{"login":"pkuphy","createTime":1620786176634},"zhangjihu0":{"login":"zhangjihu0","createTime":1620786176634},"w-z-hub":{"login":"w-z-hub","createTime":1620786176634},"bmxbmx3":{"login":"bmxbmx3","createTime":1620786176634},"Lizhao-Liu":{"login":"Lizhao-Liu","createTime":1620786176634},"terrylijiayang":{"login":"terrylijiayang","createTime":1620786176634},"shizukanaskytree":{"login":"shizukanaskytree","createTime":1620786176634},"taozi-taozi":{"login":"taozi-taozi","createTime":1620786176634},"wanyongtao1988":{"login":"wanyongtao1988","createTime":1620786176634},"lzdFeiFei":{"login":"lzdFeiFei","createTime":1620786176634},"angusgenius":{"login":"angusgenius","createTime":1620786176635},"lilyzhaoyilu":{"login":"lilyzhaoyilu","createTime":1620786176635},"FlorenceLLL":{"login":"FlorenceLLL","createTime":1620786176635},"zjsj":{"login":"zjsj","createTime":1620786176635},"wz-hub":{"login":"wz-hub","createTime":1620786176635},"Lizhao-Liu ":{"login":"Lizhao-Liu ","createTime":1620786176635},"LzdFeiFei":{"login":"LzdFeiFei","createTime":1620786176635},"ningali":{"login":"ningali","createTime":1620786176635},"WIN0624":{"login":"WIN0624","createTime":1620786176635},"Gjts":{"login":"Gjts","createTime":1620786176635},"CoreJa":{"login":"CoreJa","createTime":1620786176635},"FontEndArt":{"login":"FontEndArt","createTime":1620786176635},"surahe":{"login":"surahe","createTime":1620786176635},"flagyk5":{"login":"flagyk5","createTime":1620786176635},"QiYang03101994":{"login":"QiYang03101994","createTime":1620786176635},"cecilia-vu":{"login":"cecilia-vu","createTime":1620786176635},"keepchasing":{"login":"keepchasing","createTime":1620786176635},"Davont":{"login":"Davont","createTime":1620786176635},"Jolins":{"login":"Jolins","createTime":1620786176635},"cicihou":{"login":"cicihou","createTime":1620786176635},"Yueqi-19":{"login":"Yueqi-19","createTime":1620786176635},"Xeraphinite":{"login":"Xeraphinite","createTime":1620786176635},"rfhklwt":{"login":"rfhklwt","createTime":1620786176635},"Liuqibaa":{"login":"Liuqibaa","createTime":1620786176635},"Mvbbb":{"login":"Mvbbb","createTime":1620786176635},"nanwy":{"login":"nanwy","createTime":1620786176635},"zengwmFE":{"login":"zengwmFE","createTime":1620786176635},"XiaoY0324":{"login":"XiaoY0324","createTime":1620786176635},"aouos":{"login":"aouos","createTime":1620786176635},"15399618796":{"login":"15399618796","createTime":1620786176635},"LeiLeiW825":{"login":"LeiLeiW825","createTime":1620786176635},"CurrrryChen":{"login":"CurrrryChen","createTime":1620786176635},"DoubleW2w":{"login":"DoubleW2w","createTime":1620786176635},"yaofaqian":{"login":"yaofaqian","createTime":1620786176635},"fakerbaby":{"login":"fakerbaby","createTime":1620786176635},"ezrealcong":{"login":"ezrealcong","createTime":1620786176635},"PeopleWhoListenToStories":{"login":"PeopleWhoListenToStories","createTime":1620786176635},"heartinn":{"login":"heartinn","createTime":1620786176635},"XUHUIisxh":{"login":"XUHUIisxh","createTime":1620786176635},"peterolive":{"login":"peterolive","createTime":1620786176635},"bowlofnoodles":{"login":"bowlofnoodles","createTime":1620786176635},"coke420":{"login":"coke420","createTime":1620786176635},"joriscai":{"login":"joriscai","createTime":1620786176635},"348977787@qq.com":{"login":"348977787@qq.com","createTime":1620786176635},"miqpalzm":{"login":"miqpalzm","createTime":1620786176635},"sitequ":{"login":"sitequ","createTime":1620786176635},"dorothyDing":{"login":"dorothyDing","createTime":1620786176635},"BraveSage":{"login":"BraveSage","createTime":1620786176635},"edge-wzw":{"login":"edge-wzw","createTime":1620786176635},"dublue24":{"login":"dublue24","createTime":1620786176635},"Xyxy1722":{"login":"Xyxy1722","createTime":1620786176635},"mystoryshine":{"login":"mystoryshine","createTime":1620786176635},"wangyi123456":{"login":"wangyi123456","createTime":1620786176635},"mittacy":{"login":"mittacy","createTime":1620786176635},"Nicenonecb":{"login":"Nicenonecb","createTime":1620786176635},"LangqiZhao":{"login":"LangqiZhao","createTime":1620786176635},"wangpengzhen":{"login":"wangpengzhen","createTime":1620786176635},"falconruo":{"login":"falconruo","createTime":1620786176635},"mokinzhao":{"login":"mokinzhao","createTime":1620786176635},"zhangyong-hub":{"login":"zhangyong-hub","createTime":1620786176635},"125110072@qq.com":{"login":"125110072@qq.com","createTime":1620786176635},"wsgouwan":{"login":"wsgouwan","createTime":1620786176635},"johanazhu":{"login":"johanazhu","createTime":1620786176635},"HTian1997":{"login":"HTian1997","createTime":1620786176635},"Bochengwan":{"login":"Bochengwan","createTime":1620786176635},"shuo0314":{"login":"shuo0314","createTime":1620786176635},"peacejoylove86":{"login":"peacejoylove86","createTime":1620786176635},"joe-the-plumber":{"login":"joe-the-plumber","createTime":1620786176635},"QiuhaoLi":{"login":"QiuhaoLi","createTime":1620786176635},"xiaotuanzi999":{"login":"xiaotuanzi999","createTime":1620786176635},"eachless":{"login":"eachless","createTime":1620786176635},"simplezhao":{"login":"simplezhao","createTime":1620786176635},"suukii":{"login":"suukii","createTime":1620786176635},"JohnVSD":{"login":"JohnVSD","createTime":1620786176635},"AutumnDeSea":{"login":"AutumnDeSea","createTime":1620786176635},"yulecc":{"login":"yulecc","createTime":1620786176635},"devil-lin":{"login":"devil-lin","createTime":1620786176635},"dmlseeing":{"login":"dmlseeing","createTime":1620786176635},"UCASHurui":{"login":"UCASHurui","createTime":1620786176635},"naomiwufzz":{"login":"naomiwufzz","createTime":1620786176635},"dopufol":{"login":"dopufol","createTime":1620786176635},"yinfenglin":{"login":"yinfenglin","createTime":1620786176635},"wu529778790":{"login":"wu529778790","createTime":1620786176635},"15209356689":{"login":"15209356689","createTime":1620786176635},"kofzhang":{"login":"kofzhang","createTime":1620786176635},"BryanMiracle":{"login":"BryanMiracle","createTime":1620786176636},"sichenguo":{"login":"sichenguo","createTime":1620786176636},"Endeavor-Gcl":{"login":"Endeavor-Gcl","createTime":1620786176636},"Syan115":{"login":"Syan115","createTime":1620786176636},"xiongyujie":{"login":"xiongyujie","createTime":1620786176636},"qycoder":{"login":"qycoder","createTime":1620786176636},"Hazelnuttt":{"login":"Hazelnuttt","createTime":1620786176636},"S-T-D":{"login":"S-T-D","createTime":1620786176636},"wangzqnb":{"login":"wangzqnb","createTime":1620786176636},"LS-King":{"login":"LS-King","createTime":1620786176636},"gjm12345":{"login":"gjm12345","createTime":1620786176636},"yanjyumoso":{"login":"yanjyumoso","createTime":1620786176636},"YuanWenLai":{"login":"YuanWenLai","createTime":1620786176636},"linzeliang1222":{"login":"linzeliang1222","createTime":1620786176636},"MellonGuan":{"login":"MellonGuan","createTime":1620786176636},"Size-of":{"login":"Size-of","createTime":1620786176636},"oborc":{"login":"oborc","createTime":1620786176636},"Daniel-Zheng":{"login":"Daniel-Zheng","createTime":1620786176636},"thisisandy":{"login":"thisisandy","createTime":1620786176636},"Yvonne1231-Wang":{"login":"Yvonne1231-Wang","createTime":1620786176636},"Gentlemancj":{"login":"Gentlemancj","createTime":1620786176636},"bolunzhang2021":{"login":"bolunzhang2021","createTime":1620786176636},"minuet-red":{"login":"minuet-red","createTime":1620786176636},"jmaStella":{"login":"jmaStella","createTime":1620786176636},"caoyuyuyu":{"login":"caoyuyuyu","createTime":1620786176636},"yolo-jane":{"login":"yolo-jane","createTime":1620786176636},"xmlb88":{"login":"xmlb88","createTime":1620786176636},"Auto-SK":{"login":"Auto-SK","createTime":1620786176636},"mengwwww":{"login":"mengwwww","createTime":1620786176636},"st2yang":{"login":"st2yang","createTime":1620786176636},"xixi-jiu":{"login":"xixi-jiu","createTime":1620786176636},"supermeohh":{"login":"supermeohh","createTime":1620786176636},"Nbambi":{"login":"Nbambi","createTime":1620786176636},"p76":{"login":"p76","createTime":1620786176636},"Talent-Rain":{"login":"Talent-Rain","createTime":1620786176636},"cyk1337":{"login":"cyk1337","createTime":1620786176636},"daidaidashixiong666":{"login":"daidaidashixiong666","createTime":1620786176636},"hannahliu-github":{"login":"hannahliu-github","createTime":1620786176636},"ImSingee":{"login":"ImSingee","createTime":1620786176636},"QiZhongdd":{"login":"QiZhongdd","createTime":1620786176636},"AmuroPeng":{"login":"AmuroPeng","createTime":1620786176636},"ShunzWu012":{"login":"ShunzWu012","createTime":1620786176636},"LiangZheCoder":{"login":"LiangZheCoder","createTime":1620786176636},"SunStrongChina":{"login":"SunStrongChina","createTime":1620786176636},"jawn-ha":{"login":"jawn-ha","createTime":1620786176636},"Serrust":{"login":"Serrust","createTime":1620786176636},"Siomarry":{"login":"Siomarry","createTime":1620786176636},"q815101630":{"login":"q815101630","createTime":1620786176636},"xuanaxuan":{"login":"xuanaxuan","createTime":1620786176636},"CruiseYuGH":{"login":"CruiseYuGH","createTime":1620786176636},"yxq1997":{"login":"yxq1997","createTime":1620786176636},"sun-unc":{"login":"sun-unc","createTime":1620786176636},"jennny06":{"login":"jennny06","createTime":1620786176636},"youyoumx":{"login":"youyoumx","createTime":1620786176636},"tipshal":{"login":"tipshal","createTime":1620786176636},"klaus0323":{"login":"klaus0323","createTime":1620786176636},"liuajingliu":{"login":"liuajingliu","createTime":1620786176636},"AMANKB":{"login":"AMANKB","createTime":1620786176636},"Rainjoy66":{"login":"Rainjoy66","createTime":1620786176636},"zsjlovelike":{"login":"zsjlovelike","createTime":1620786176636},"renziao":{"login":"renziao","createTime":1620786176636},"threedayAAAAA":{"login":"threedayAAAAA","createTime":1620786176636},"XinlingQiu":{"login":"XinlingQiu","createTime":1620786176636},"winterdogdog":{"login":"winterdogdog","createTime":1620786176636},"xiaoyuhai":{"login":"xiaoyuhai","createTime":1620786176636},"AnnabellHyx":{"login":"AnnabellHyx","createTime":1620786176636},"luckyyangrun":{"login":"luckyyangrun","createTime":1620786176636},"Yueqi_19":{"login":"Yueqi_19","createTime":1620786176636},"raoshuang":{"login":"raoshuang","createTime":1620786176636},"Ben-Lee95":{"login":"Ben-Lee95","createTime":1620786176636},"YanFaFa":{"login":"YanFaFa","createTime":1620786176636},"mm12344":{"login":"mm12344","createTime":1620786176636},"a-enll1":{"login":"a-enll1","createTime":1620786176636},"breadfruit":{"login":"breadfruit","createTime":1620786176636},"prince805962788":{"login":"prince805962788","createTime":1620786176636},"shmilywh":{"login":"shmilywh","createTime":1620786176636},"JadeQi":{"login":"JadeQi","createTime":1620786176636},"xqmmy":{"login":"xqmmy","createTime":1620786176636},"zfaye":{"login":"zfaye","createTime":1620786176636},"nweass":{"login":"nweass","createTime":1620786176636},"LambertCao":{"login":"LambertCao","createTime":1620786176636},"YuetongYu":{"login":"YuetongYu","createTime":1620786176636},"kernelSue":{"login":"kernelSue","createTime":1620786176636},"RMsboy":{"login":"RMsboy","createTime":1620786176636},"ZiyangZ":{"login":"ZiyangZ","createTime":1620786176637},"baoqin87":{"login":"baoqin87","createTime":1620786176637},"RealDuxy":{"login":"RealDuxy","createTime":1620786176637},"NealChristmas":{"login":"NealChristmas","createTime":1620786176637},"zibinanhai":{"login":"zibinanhai","createTime":1620786176637},"flashyy":{"login":"flashyy","createTime":1620786176637},"ysy0707":{"login":"ysy0707","createTime":1620786176637},"luoluomo":{"login":"luoluomo","createTime":1620786176637},"mayu0007":{"login":"mayu0007","createTime":1620786176637},"caimaoy":{"login":"caimaoy","createTime":1620786176637},"CelesteXiong":{"login":"CelesteXiong","createTime":1620786176637},"maqianxiong":{"login":"maqianxiong","createTime":1620786176637},"mosihan":{"login":"mosihan","createTime":1620786176637},"dpgirl":{"login":"dpgirl","createTime":1620786176637},"prhCSer":{"login":"prhCSer","createTime":1620786176637},"rufengnanren":{"login":"rufengnanren","createTime":1620786176637},"Peg-008":{"login":"Peg-008","createTime":1620786176637},"NorthSeacoder":{"login":"NorthSeacoder","createTime":1620786176637},"theonebemine":{"login":"theonebemine","createTime":1620786723140},"Moin-Jer":{"login":"Moin-Jer","createTime":1620786723140},"a-enll":{"login":"a-enll","createTime":1620788905880},"Dark-volute":{"login":"Dark-volute","createTime":1620811349699},"wangyifan2018":{"login":"wangyifan2018","createTime":1620811349699},"jueran":{"login":"jueran","createTime":1620811349699},"52HzEcho":{"login":"52HzEcho","createTime":1620811349699},"unclegem":{"login":"unclegem","createTime":1620827927020},"feikerwu":{"login":"feikerwu","createTime":1620827927020},"x-joey":{"login":"x-joey","createTime":1620832597718},"scarydemon2":{"login":"scarydemon2","createTime":1620832597718}}